{
  "$schema": "../node_modules/@tauri-apps/cli/config.schema.json",
  "productName": "NXmind",
  "version": "0.5.6",
  "identifier": "com.thehuan.nxmind",
  "build": {
    "frontendDist": "../dist",
    "devUrl": "http://localhost:1420",
    "beforeDevCommand": "npm run dev",
    "beforeBuildCommand": "npm run build"
  },
  "app": {
    "windows": [
      {
        "title": "心流导图",
        "label": "main",
        "width": 1024,
        "height": 768,
        "resizable": true,
        "fullscreen": false,
        "decorations": false,
        "transparent": false,
        "dragDropEnabled": false,
        "visible": false
      }
    ],
    "security": {
      "csp": null
    }
  },
  "bundle": {
    "active": true,
    "targets": [
      "nsis"
    ],
    "icon": [
      "icons/32x32.png",
      "icons/128x128.png",
      "icons/128x128@2x.png",
      "icons/icon.icns",
      "icons/icon.ico"
    ]
  }
}